{
"type": "FeatureCollection",
"crs": { "type": "name", "properties": { "name": "urn:ogc:def:crs:OGC:1.3:CRS84" } },
                                                                                
"features": [
{ "type": "Feature", "properties": { "Primary ID": "1.26", "Secondary ID": "7km NE of Lake Arrowhead, California" }, "geometry": { "type": "Point", "coordinates": [ -84.328008, 33.7993178] } },
{ "type": "Feature", "geometry": { "type": "Point", "coordinates": [ -84.3733132, 33.8486731 ] } }
]}